NovelAILLMWrapper/GenerationSettings.py
NovelAILLMWrapper/NovelAILLM.py
NovelAILLMWrapper/__init__.py
NovelAILLMWrapper/boilerplate.py
NovelAILLMWrapper-0.105.dist-info/METADATA
NovelAILLMWrapper-0.105.dist-info/WHEEL
NovelAILLMWrapper-0.105.dist-info/top_level.txt
NovelAILLMWrapper-0.105.dist-info/RECORD
