Metadata-Version: 2.1
Name: NovelAILLMWrapper
Version: 0.105
Requires-Dist: aiodns ==3.1.0
Requires-Dist: aiohttp ==3.8.6
Requires-Dist: aiosignal ==1.3.1
Requires-Dist: annotated-types ==0.6.0
Requires-Dist: anyio ==3.7.1
Requires-Dist: argon2-cffi ==21.3.0
Requires-Dist: argon2-cffi-bindings ==21.2.0
Requires-Dist: async-timeout ==4.0.3
Requires-Dist: attrs ==23.1.0
Requires-Dist: Brotli ==1.1.0
Requires-Dist: build ==0.10.0
Requires-Dist: CacheControl ==0.13.1
Requires-Dist: cchardet ==2.1.7
Requires-Dist: certifi ==2023.7.22
Requires-Dist: cffi ==1.16.0
Requires-Dist: charset-normalizer ==3.3.0
Requires-Dist: cleo ==2.0.1
Requires-Dist: colorama ==0.4.6
Requires-Dist: crashtest ==0.4.1
Requires-Dist: dataclasses-json ==0.6.1
Requires-Dist: distlib ==0.3.7
Requires-Dist: dulwich ==0.21.6
Requires-Dist: exceptiongroup ==1.1.3
Requires-Dist: filelock ==3.12.4
Requires-Dist: frozenlist ==1.4.0
Requires-Dist: ftfy ==6.1.1
Requires-Dist: greenlet ==3.0.0
Requires-Dist: idna ==3.4
Requires-Dist: importlib-metadata ==6.8.0
Requires-Dist: installer ==0.7.0
Requires-Dist: jaraco.classes ==3.3.0
Requires-Dist: jsonpatch ==1.33
Requires-Dist: jsonpointer ==2.4
Requires-Dist: jsonschema ==4.17.3
Requires-Dist: keyring ==24.2.0
Requires-Dist: langchain ==0.0.310
Requires-Dist: langsmith ==0.0.43
Requires-Dist: marshmallow ==3.20.1
Requires-Dist: more-itertools ==10.1.0
Requires-Dist: msgpack ==1.0.7
Requires-Dist: multidict ==6.0.4
Requires-Dist: mypy-extensions ==1.0.0
Requires-Dist: novelai-api ==0.19.0
Requires-Dist: numpy ==1.26.0
Requires-Dist: packaging ==23.2
Requires-Dist: pexpect ==4.8.0
Requires-Dist: Pillow ==9.5.0
Requires-Dist: pkginfo ==1.9.6
Requires-Dist: platformdirs ==3.11.0
Requires-Dist: poetry ==1.6.1
Requires-Dist: poetry-core ==1.7.0
Requires-Dist: poetry-plugin-export ==1.5.0
Requires-Dist: ptyprocess ==0.7.0
Requires-Dist: pycares ==4.4.0
Requires-Dist: pycparser ==2.21
Requires-Dist: pydantic ==2.4.2
Requires-Dist: pydantic-core ==2.10.1
Requires-Dist: PyNaCl ==1.5.0
Requires-Dist: pyproject-hooks ==1.0.0
Requires-Dist: pyrsistent ==0.19.3
Requires-Dist: python-dotenv ==1.0.0
Requires-Dist: pywin32-ctypes ==0.2.2
Requires-Dist: PyYAML ==6.0.1
Requires-Dist: rapidfuzz ==2.15.2
Requires-Dist: regex ==2022.10.31
Requires-Dist: requests ==2.31.0
Requires-Dist: requests-toolbelt ==1.0.0
Requires-Dist: sentencepiece ==0.1.99
Requires-Dist: shellingham ==1.5.3
Requires-Dist: sniffio ==1.3.0
Requires-Dist: SQLAlchemy ==2.0.21
Requires-Dist: tenacity ==8.2.3
Requires-Dist: tokenizers ==0.13.3
Requires-Dist: tomli ==2.0.1
Requires-Dist: tomlkit ==0.12.1
Requires-Dist: trove-classifiers ==2023.9.19
Requires-Dist: typing-inspect ==0.9.0
Requires-Dist: typing-extensions ==4.8.0
Requires-Dist: urllib3 ==2.0.6
Requires-Dist: virtualenv ==20.24.5
Requires-Dist: wcwidth ==0.2.8
Requires-Dist: yarl ==1.9.2
Requires-Dist: zipp ==3.17.0
